{"game_id":"110303581088462651","match_id":"110303581088462650","league":"LCS","start_time":"2023-07-14T22:00:00Z","blue_team":"100T","red_team":"TSM","summary":{"blue_total_kills":20,"red_total_kills":2,"blue_time_to_5":19.163583333333335,"red_time_to_5":null,"blue_kills_at_10min":3,"red_kills_at_10min":0,"blue_kills_at_15min":3,"red_kills_at_15min":1,"first_to_five":"blue"},"kills":[{"side":"blue","kill_num":1,"t_secs":249.714,"ts":"2023-07-14T22:03:49.714Z"},{"side":"blue","kill_num":2,"t_secs":449.978,"ts":"2023-07-14T22:07:09.978Z"},{"side":"blue","kill_num":3,"t_secs":529.711,"ts":"2023-07-14T22:08:29.711Z"},{"side":"red","kill_num":1,"t_secs":689.717,"ts":"2023-07-14T22:11:09.717Z"},{"side":"blue","kill_num":4,"t_secs":1149.815,"ts":"2023-07-14T22:18:49.815Z"},{"side":"blue","kill_num":5,"t_secs":1149.815,"ts":"2023-07-14T22:18:49.815Z"},{"side":"red","kill_num":2,"t_secs":1159.707,"ts":"2023-07-14T22:18:59.707Z"},{"side":"blue","kill_num":6,"t_secs":1209.877,"ts":"2023-07-14T22:19:49.877Z"},{"side":"blue","kill_num":7,"t_secs":1209.877,"ts":"2023-07-14T22:19:49.877Z"},{"side":"blue","kill_num":8,"t_secs":1209.877,"ts":"2023-07-14T22:19:49.877Z"},{"side":"blue","kill_num":9,"t_secs":1219.975,"ts":"2023-07-14T22:19:59.975Z"},{"side":"blue","kill_num":10,"t_secs":1229.986,"ts":"2023-07-14T22:20:09.986Z"},{"side":"blue","kill_num":11,"t_secs":1309.729,"ts":"2023-07-14T22:21:29.729Z"},{"side":"blue","kill_num":12,"t_secs":1309.729,"ts":"2023-07-14T22:21:29.729Z"},{"side":"blue","kill_num":13,"t_secs":1309.729,"ts":"2023-07-14T22:21:29.729Z"},{"side":"blue","kill_num":14,"t_secs":1359.839,"ts":"2023-07-14T22:22:19.839Z"},{"side":"blue","kill_num":15,"t_secs":1369.978,"ts":"2023-07-14T22:22:29.978Z"},{"side":"blue","kill_num":16,"t_secs":1429.729,"ts":"2023-07-14T22:23:29.729Z"},{"side":"blue","kill_num":17,"t_secs":1429.729,"ts":"2023-07-14T22:23:29.729Z"},{"side":"blue","kill_num":18,"t_secs":1429.729,"ts":"2023-07-14T22:23:29.729Z"},{"side":"blue","kill_num":19,"t_secs":1429.729,"ts":"2023-07-14T22:23:29.729Z"},{"side":"blue","kill_num":20,"t_secs":1439.918,"ts":"2023-07-14T22:23:39.918Z"}]}