{"game_id":"110909366081176380","match_id":"110909366081176378","league":"LCK","start_time":"2023-08-24T08:00:00Z","blue_team":"KT","red_team":"HLE","summary":{"blue_total_kills":8,"red_total_kills":12,"blue_time_to_5":19.998683333333336,"red_time_to_5":16.9965,"blue_kills_at_10min":0,"red_kills_at_10min":0,"blue_kills_at_15min":3,"red_kills_at_15min":4,"first_to_five":"red"},"kills":[{"side":"blue","kill_num":1,"t_secs":789.416,"ts":"2023-08-24T09:13:49.416Z"},{"side":"red","kill_num":1,"t_secs":799.798,"ts":"2023-08-24T09:13:59.798Z"},{"side":"blue","kill_num":2,"t_secs":809.999,"ts":"2023-08-24T09:14:09.999Z"},{"side":"red","kill_num":2,"t_secs":809.999,"ts":"2023-08-24T09:14:09.999Z"},{"side":"red","kill_num":3,"t_secs":819.407,"ts":"2023-08-24T09:14:19.407Z"},{"side":"red","kill_num":4,"t_secs":819.407,"ts":"2023-08-24T09:14:19.407Z"},{"side":"blue","kill_num":3,"t_secs":839.427,"ts":"2023-08-24T09:14:39.427Z"},{"side":"red","kill_num":5,"t_secs":1019.79,"ts":"2023-08-24T09:17:39.790Z"},{"side":"blue","kill_num":4,"t_secs":1179.745,"ts":"2023-08-24T09:20:19.745Z"},{"side":"red","kill_num":6,"t_secs":1179.745,"ts":"2023-08-24T09:20:19.745Z"},{"side":"red","kill_num":7,"t_secs":1189.945,"ts":"2023-08-24T09:20:29.945Z"},{"side":"red","kill_num":8,"t_secs":1189.945,"ts":"2023-08-24T09:20:29.945Z"},{"side":"blue","kill_num":5,"t_secs":1199.921,"ts":"2023-08-24T09:20:39.921Z"},{"side":"red","kill_num":9,"t_secs":1199.921,"ts":"2023-08-24T09:20:39.921Z"},{"side":"blue","kill_num":6,"t_secs":1379.808,"ts":"2023-08-24T09:23:39.808Z"},{"side":"red","kill_num":10,"t_secs":1519.76,"ts":"2023-08-24T09:25:59.760Z"},{"side":"red","kill_num":11,"t_secs":1529.874,"ts":"2023-08-24T09:26:09.874Z"},{"side":"red","kill_num":12,"t_secs":1539.852,"ts":"2023-08-24T09:26:19.852Z"},{"side":"blue","kill_num":7,"t_secs":1549.553,"ts":"2023-08-24T09:26:29.553Z"},{"side":"blue","kill_num":8,"t_secs":1549.553,"ts":"2023-08-24T09:26:29.553Z"}]}