{"game_id":"111561319410825158","match_id":"111561319410825157","league":"LPL","start_time":"2024-02-18T07:00:00Z","blue_team":"NIP","red_team":"UP","summary":{"blue_total_kills":11,"red_total_kills":2,"blue_time_to_5":15.32415,"red_time_to_5":null,"blue_kills_at_10min":2,"red_kills_at_10min":1,"blue_kills_at_15min":4,"red_kills_at_15min":1,"first_to_five":"blue"},"kills":[{"side":"blue","kill_num":1,"t_secs":439.927,"ts":"2024-02-18T07:27:29.927Z"},{"side":"red","kill_num":1,"t_secs":449.712,"ts":"2024-02-18T07:27:39.712Z"},{"side":"blue","kill_num":2,"t_secs":579.47,"ts":"2024-02-18T07:29:49.470Z"},{"side":"blue","kill_num":3,"t_secs":649.457,"ts":"2024-02-18T07:30:59.457Z"},{"side":"blue","kill_num":4,"t_secs":669.715,"ts":"2024-02-18T07:31:19.715Z"},{"side":"blue","kill_num":5,"t_secs":919.449,"ts":"2024-02-18T07:35:29.449Z"},{"side":"blue","kill_num":6,"t_secs":1419.943,"ts":"2024-02-18T07:43:49.943Z"},{"side":"blue","kill_num":7,"t_secs":1429.843,"ts":"2024-02-18T07:43:59.843Z"},{"side":"blue","kill_num":8,"t_secs":1779.66,"ts":"2024-02-18T07:49:49.660Z"},{"side":"blue","kill_num":9,"t_secs":1789.987,"ts":"2024-02-18T07:49:59.987Z"},{"side":"blue","kill_num":10,"t_secs":1789.987,"ts":"2024-02-18T07:49:59.987Z"},{"side":"blue","kill_num":11,"t_secs":1829.441,"ts":"2024-02-18T07:50:39.441Z"},{"side":"red","kill_num":2,"t_secs":1829.441,"ts":"2024-02-18T07:50:39.441Z"}]}