{"game_id":"111561319410759122","match_id":"111561319410759121","league":"LPL","start_time":"2024-03-07T07:00:00Z","blue_team":"AL","red_team":"RA","summary":{"blue_total_kills":14,"red_total_kills":5,"blue_time_to_5":24.1648,"red_time_to_5":28.331933333333332,"blue_kills_at_10min":1,"red_kills_at_10min":1,"blue_kills_at_15min":2,"red_kills_at_15min":1,"first_to_five":"blue"},"kills":[{"side":"blue","kill_num":1,"t_secs":249.825,"ts":"2024-03-07T07:20:29.825Z"},{"side":"red","kill_num":1,"t_secs":459.736,"ts":"2024-03-07T07:23:59.736Z"},{"side":"blue","kill_num":2,"t_secs":769.515,"ts":"2024-03-07T07:29:09.515Z"},{"side":"red","kill_num":2,"t_secs":999.977,"ts":"2024-03-07T07:32:59.977Z"},{"side":"blue","kill_num":3,"t_secs":1099.764,"ts":"2024-03-07T07:34:39.764Z"},{"side":"blue","kill_num":4,"t_secs":1099.764,"ts":"2024-03-07T07:34:39.764Z"},{"side":"red","kill_num":3,"t_secs":1299.414,"ts":"2024-03-07T07:37:59.414Z"},{"side":"blue","kill_num":5,"t_secs":1449.888,"ts":"2024-03-07T07:40:29.888Z"},{"side":"blue","kill_num":6,"t_secs":1449.888,"ts":"2024-03-07T07:40:29.888Z"},{"side":"blue","kill_num":7,"t_secs":1449.888,"ts":"2024-03-07T07:40:29.888Z"},{"side":"blue","kill_num":8,"t_secs":1449.888,"ts":"2024-03-07T07:40:29.888Z"},{"side":"red","kill_num":4,"t_secs":1449.888,"ts":"2024-03-07T07:40:29.888Z"},{"side":"blue","kill_num":9,"t_secs":1459.949,"ts":"2024-03-07T07:40:39.949Z"},{"side":"blue","kill_num":10,"t_secs":1699.916,"ts":"2024-03-07T07:44:39.916Z"},{"side":"red","kill_num":5,"t_secs":1699.916,"ts":"2024-03-07T07:44:39.916Z"},{"side":"blue","kill_num":11,"t_secs":1709.771,"ts":"2024-03-07T07:44:49.771Z"},{"side":"blue","kill_num":12,"t_secs":1709.771,"ts":"2024-03-07T07:44:49.771Z"},{"side":"blue","kill_num":13,"t_secs":1719.407,"ts":"2024-03-07T07:44:59.407Z"},{"side":"blue","kill_num":14,"t_secs":1729.426,"ts":"2024-03-07T07:45:09.426Z"}]}