{"game_id":"111561319410759488","match_id":"111561319410759485","league":"LPL","start_time":"2024-02-01T11:00:00Z","blue_team":"LNG","red_team":"WBG","summary":{"blue_total_kills":17,"red_total_kills":9,"blue_time_to_5":18.496133333333333,"red_time_to_5":19.995966666666668,"blue_kills_at_10min":1,"red_kills_at_10min":0,"blue_kills_at_15min":2,"red_kills_at_15min":1,"first_to_five":"blue"},"kills":[{"side":"blue","kill_num":1,"t_secs":579.762,"ts":"2024-02-01T13:31:19.762Z"},{"side":"blue","kill_num":2,"t_secs":669.999,"ts":"2024-02-01T13:32:49.999Z"},{"side":"red","kill_num":1,"t_secs":859.974,"ts":"2024-02-01T13:35:59.974Z"},{"side":"blue","kill_num":3,"t_secs":989.757,"ts":"2024-02-01T13:38:09.757Z"},{"side":"red","kill_num":2,"t_secs":1009.962,"ts":"2024-02-01T13:38:29.962Z"},{"side":"blue","kill_num":4,"t_secs":1099.999,"ts":"2024-02-01T13:39:59.999Z"},{"side":"red","kill_num":3,"t_secs":1099.999,"ts":"2024-02-01T13:39:59.999Z"},{"side":"blue","kill_num":5,"t_secs":1109.768,"ts":"2024-02-01T13:40:09.768Z"},{"side":"red","kill_num":4,"t_secs":1199.758,"ts":"2024-02-01T13:41:39.758Z"},{"side":"red","kill_num":5,"t_secs":1199.758,"ts":"2024-02-01T13:41:39.758Z"},{"side":"blue","kill_num":6,"t_secs":1209.776,"ts":"2024-02-01T13:41:49.776Z"},{"side":"blue","kill_num":7,"t_secs":1479.786,"ts":"2024-02-01T13:46:19.786Z"},{"side":"blue","kill_num":8,"t_secs":1519.781,"ts":"2024-02-01T13:46:59.781Z"},{"side":"blue","kill_num":9,"t_secs":1519.781,"ts":"2024-02-01T13:46:59.781Z"},{"side":"red","kill_num":6,"t_secs":1519.781,"ts":"2024-02-01T13:46:59.781Z"},{"side":"red","kill_num":7,"t_secs":1859.911,"ts":"2024-02-01T13:52:39.911Z"},{"side":"blue","kill_num":10,"t_secs":1889.804,"ts":"2024-02-01T13:53:09.804Z"},{"side":"blue","kill_num":11,"t_secs":2079.83,"ts":"2024-02-01T13:56:19.830Z"},{"side":"blue","kill_num":12,"t_secs":2089.759,"ts":"2024-02-01T13:56:29.759Z"},{"side":"red","kill_num":8,"t_secs":2089.759,"ts":"2024-02-01T13:56:29.759Z"},{"side":"blue","kill_num":13,"t_secs":2269.85,"ts":"2024-02-01T13:59:29.850Z"},{"side":"blue","kill_num":14,"t_secs":2299.8,"ts":"2024-02-01T13:59:59.800Z"},{"side":"blue","kill_num":15,"t_secs":2299.8,"ts":"2024-02-01T13:59:59.800Z"},{"side":"blue","kill_num":16,"t_secs":2299.8,"ts":"2024-02-01T13:59:59.800Z"},{"side":"red","kill_num":9,"t_secs":2299.8,"ts":"2024-02-01T13:59:59.800Z"},{"side":"blue","kill_num":17,"t_secs":2309.779,"ts":"2024-02-01T14:00:09.779Z"}]}