{"game_id":"111561319410759247","match_id":"111561319410759245","league":"LPL","start_time":"2024-02-19T11:00:00Z","blue_team":"EDG","red_team":"WE","summary":{"blue_total_kills":11,"red_total_kills":3,"blue_time_to_5":18.826466666666665,"red_time_to_5":null,"blue_kills_at_10min":2,"red_kills_at_10min":0,"blue_kills_at_15min":4,"red_kills_at_15min":0,"first_to_five":"blue"},"kills":[{"side":"blue","kill_num":1,"t_secs":279.81,"ts":"2024-02-19T12:33:49.810Z"},{"side":"blue","kill_num":2,"t_secs":289.587,"ts":"2024-02-19T12:33:59.587Z"},{"side":"blue","kill_num":3,"t_secs":699.912,"ts":"2024-02-19T12:40:49.912Z"},{"side":"blue","kill_num":4,"t_secs":709.849,"ts":"2024-02-19T12:40:59.849Z"},{"side":"red","kill_num":1,"t_secs":1039.57,"ts":"2024-02-19T12:46:29.570Z"},{"side":"blue","kill_num":5,"t_secs":1129.588,"ts":"2024-02-19T12:47:59.588Z"},{"side":"blue","kill_num":6,"t_secs":1309.797,"ts":"2024-02-19T12:50:59.797Z"},{"side":"blue","kill_num":7,"t_secs":1619.566,"ts":"2024-02-19T12:56:09.566Z"},{"side":"blue","kill_num":8,"t_secs":1689.7,"ts":"2024-02-19T12:57:19.700Z"},{"side":"blue","kill_num":9,"t_secs":1759.748,"ts":"2024-02-19T12:58:29.748Z"},{"side":"blue","kill_num":10,"t_secs":1759.748,"ts":"2024-02-19T12:58:29.748Z"},{"side":"red","kill_num":2,"t_secs":1759.748,"ts":"2024-02-19T12:58:29.748Z"},{"side":"blue","kill_num":11,"t_secs":1769.575,"ts":"2024-02-19T12:58:39.575Z"},{"side":"red","kill_num":3,"t_secs":1769.575,"ts":"2024-02-19T12:58:39.575Z"}]}