{"game_id":"111997906552104665","match_id":"111997906552104664","league":"LEC","start_time":"2024-03-22T17:30:00Z","blue_team":"G2","red_team":"SK","summary":{"blue_total_kills":15,"red_total_kills":4,"blue_time_to_5":19.325483333333334,"red_time_to_5":null,"blue_kills_at_10min":1,"red_kills_at_10min":0,"blue_kills_at_15min":2,"red_kills_at_15min":1,"first_to_five":"blue"},"kills":[{"side":"blue","kill_num":1,"t_secs":189.758,"ts":"2024-03-22T17:47:19.758Z"},{"side":"blue","kill_num":2,"t_secs":719.919,"ts":"2024-03-22T17:56:09.919Z"},{"side":"red","kill_num":1,"t_secs":719.919,"ts":"2024-03-22T17:56:09.919Z"},{"side":"blue","kill_num":3,"t_secs":1139.494,"ts":"2024-03-22T18:03:09.494Z"},{"side":"blue","kill_num":4,"t_secs":1149.799,"ts":"2024-03-22T18:03:19.799Z"},{"side":"red","kill_num":2,"t_secs":1149.799,"ts":"2024-03-22T18:03:19.799Z"},{"side":"blue","kill_num":5,"t_secs":1159.529,"ts":"2024-03-22T18:03:29.529Z"},{"side":"blue","kill_num":6,"t_secs":1329.995,"ts":"2024-03-22T18:06:19.995Z"},{"side":"blue","kill_num":7,"t_secs":1409.502,"ts":"2024-03-22T18:07:39.502Z"},{"side":"blue","kill_num":8,"t_secs":1519.908,"ts":"2024-03-22T18:09:29.908Z"},{"side":"red","kill_num":3,"t_secs":1519.908,"ts":"2024-03-22T18:09:29.908Z"},{"side":"blue","kill_num":9,"t_secs":1529.768,"ts":"2024-03-22T18:09:39.768Z"},{"side":"blue","kill_num":10,"t_secs":1529.768,"ts":"2024-03-22T18:09:39.768Z"},{"side":"blue","kill_num":11,"t_secs":1539.658,"ts":"2024-03-22T18:09:49.658Z"},{"side":"blue","kill_num":12,"t_secs":1539.658,"ts":"2024-03-22T18:09:49.658Z"},{"side":"blue","kill_num":13,"t_secs":1639.507,"ts":"2024-03-22T18:11:29.507Z"},{"side":"blue","kill_num":14,"t_secs":1679.942,"ts":"2024-03-22T18:12:09.942Z"},{"side":"blue","kill_num":15,"t_secs":1689.65,"ts":"2024-03-22T18:12:19.650Z"},{"side":"red","kill_num":4,"t_secs":1689.65,"ts":"2024-03-22T18:12:19.650Z"}]}