{"game_id":"112274705999884308","match_id":"112274705999884304","league":"MSI","start_time":"2024-05-11T04:00:00Z","blue_team":"FNC","red_team":"TLAW","summary":{"blue_total_kills":6,"red_total_kills":17,"blue_time_to_5":23.165599999999998,"red_time_to_5":22.83175,"blue_kills_at_10min":1,"red_kills_at_10min":1,"blue_kills_at_15min":3,"red_kills_at_15min":2,"first_to_five":"red"},"kills":[{"side":"blue","kill_num":1,"t_secs":399.922,"ts":"2024-05-11T06:43:09.922Z"},{"side":"red","kill_num":1,"t_secs":409.928,"ts":"2024-05-11T06:43:19.928Z"},{"side":"blue","kill_num":2,"t_secs":699.921,"ts":"2024-05-11T06:48:09.921Z"},{"side":"blue","kill_num":3,"t_secs":709.904,"ts":"2024-05-11T06:48:19.904Z"},{"side":"red","kill_num":2,"t_secs":739.926,"ts":"2024-05-11T06:48:49.926Z"},{"side":"red","kill_num":3,"t_secs":909.926,"ts":"2024-05-11T06:51:39.926Z"},{"side":"blue","kill_num":4,"t_secs":1139.936,"ts":"2024-05-11T06:55:29.936Z"},{"side":"red","kill_num":4,"t_secs":1179.931,"ts":"2024-05-11T06:56:09.931Z"},{"side":"red","kill_num":5,"t_secs":1369.905,"ts":"2024-05-11T06:59:19.905Z"},{"side":"red","kill_num":6,"t_secs":1379.947,"ts":"2024-05-11T06:59:29.947Z"},{"side":"red","kill_num":7,"t_secs":1379.947,"ts":"2024-05-11T06:59:29.947Z"},{"side":"blue","kill_num":5,"t_secs":1389.936,"ts":"2024-05-11T06:59:39.936Z"},{"side":"red","kill_num":8,"t_secs":1389.936,"ts":"2024-05-11T06:59:39.936Z"},{"side":"red","kill_num":9,"t_secs":1519.932,"ts":"2024-05-11T07:01:49.932Z"},{"side":"blue","kill_num":6,"t_secs":1539.929,"ts":"2024-05-11T07:02:09.929Z"},{"side":"red","kill_num":10,"t_secs":1539.929,"ts":"2024-05-11T07:02:09.929Z"},{"side":"red","kill_num":11,"t_secs":1549.921,"ts":"2024-05-11T07:02:19.921Z"},{"side":"red","kill_num":12,"t_secs":1549.921,"ts":"2024-05-11T07:02:19.921Z"},{"side":"red","kill_num":13,"t_secs":1549.921,"ts":"2024-05-11T07:02:19.921Z"},{"side":"red","kill_num":14,"t_secs":1699.94,"ts":"2024-05-11T07:04:49.940Z"},{"side":"red","kill_num":15,"t_secs":1699.94,"ts":"2024-05-11T07:04:49.940Z"},{"side":"red","kill_num":16,"t_secs":1729.911,"ts":"2024-05-11T07:05:19.911Z"},{"side":"red","kill_num":17,"t_secs":1729.911,"ts":"2024-05-11T07:05:19.911Z"}]}