{"game_id":"112274705999884307","match_id":"112274705999884304","league":"MSI","start_time":"2024-05-11T04:00:00Z","blue_team":"FNC","red_team":"TLAW","summary":{"blue_total_kills":20,"red_total_kills":9,"blue_time_to_5":14.333300000000001,"red_time_to_5":18.3324,"blue_kills_at_10min":4,"red_kills_at_10min":2,"blue_kills_at_15min":6,"red_kills_at_15min":3,"first_to_five":"blue"},"kills":[{"side":"blue","kill_num":1,"t_secs":69.601,"ts":"2024-05-11T05:48:59.601Z"},{"side":"red","kill_num":1,"t_secs":69.601,"ts":"2024-05-11T05:48:59.601Z"},{"side":"blue","kill_num":2,"t_secs":379.798,"ts":"2024-05-11T05:54:09.798Z"},{"side":"red","kill_num":2,"t_secs":389.63,"ts":"2024-05-11T05:54:19.630Z"},{"side":"blue","kill_num":3,"t_secs":589.985,"ts":"2024-05-11T05:57:39.985Z"},{"side":"blue","kill_num":4,"t_secs":599.928,"ts":"2024-05-11T05:57:49.928Z"},{"side":"blue","kill_num":5,"t_secs":859.998,"ts":"2024-05-11T06:02:09.998Z"},{"side":"blue","kill_num":6,"t_secs":859.998,"ts":"2024-05-11T06:02:09.998Z"},{"side":"red","kill_num":3,"t_secs":859.998,"ts":"2024-05-11T06:02:09.998Z"},{"side":"red","kill_num":4,"t_secs":1099.944,"ts":"2024-05-11T06:06:09.944Z"},{"side":"red","kill_num":5,"t_secs":1099.944,"ts":"2024-05-11T06:06:09.944Z"},{"side":"blue","kill_num":7,"t_secs":1239.913,"ts":"2024-05-11T06:08:29.913Z"},{"side":"red","kill_num":6,"t_secs":1239.913,"ts":"2024-05-11T06:08:29.913Z"},{"side":"blue","kill_num":8,"t_secs":1249.628,"ts":"2024-05-11T06:08:39.628Z"},{"side":"red","kill_num":7,"t_secs":1249.628,"ts":"2024-05-11T06:08:39.628Z"},{"side":"blue","kill_num":9,"t_secs":1389.608,"ts":"2024-05-11T06:10:59.608Z"},{"side":"blue","kill_num":10,"t_secs":1399.606,"ts":"2024-05-11T06:11:09.606Z"},{"side":"red","kill_num":8,"t_secs":1399.606,"ts":"2024-05-11T06:11:09.606Z"},{"side":"blue","kill_num":11,"t_secs":1409.651,"ts":"2024-05-11T06:11:19.651Z"},{"side":"blue","kill_num":12,"t_secs":1419.685,"ts":"2024-05-11T06:11:29.685Z"},{"side":"blue","kill_num":13,"t_secs":1499.624,"ts":"2024-05-11T06:12:49.624Z"},{"side":"blue","kill_num":14,"t_secs":1499.624,"ts":"2024-05-11T06:12:49.624Z"},{"side":"red","kill_num":9,"t_secs":1499.624,"ts":"2024-05-11T06:12:49.624Z"},{"side":"blue","kill_num":15,"t_secs":1509.76,"ts":"2024-05-11T06:12:59.760Z"},{"side":"blue","kill_num":16,"t_secs":1519.632,"ts":"2024-05-11T06:13:09.632Z"},{"side":"blue","kill_num":17,"t_secs":1699.807,"ts":"2024-05-11T06:16:09.807Z"},{"side":"blue","kill_num":18,"t_secs":1759.981,"ts":"2024-05-11T06:17:09.981Z"},{"side":"blue","kill_num":19,"t_secs":1759.981,"ts":"2024-05-11T06:17:09.981Z"},{"side":"blue","kill_num":20,"t_secs":1769.829,"ts":"2024-05-11T06:17:19.829Z"}]}