{"game_id":"112352881166864512","match_id":"112352881166864510","league":"LEC","start_time":"2024-07-26T15:00:00Z","blue_team":"SHFT","red_team":"KC","summary":{"blue_total_kills":17,"red_total_kills":7,"blue_time_to_5":14.6647,"red_time_to_5":19.489250000000002,"blue_kills_at_10min":1,"red_kills_at_10min":1,"blue_kills_at_15min":7,"red_kills_at_15min":3,"first_to_five":"blue"},"kills":[{"side":"blue","kill_num":1,"t_secs":529.346,"ts":"2024-07-26T16:18:19.346Z"},{"side":"red","kill_num":1,"t_secs":569.967,"ts":"2024-07-26T16:18:59.967Z"},{"side":"blue","kill_num":2,"t_secs":699.963,"ts":"2024-07-26T16:21:09.963Z"},{"side":"blue","kill_num":3,"t_secs":709.574,"ts":"2024-07-26T16:21:19.574Z"},{"side":"blue","kill_num":4,"t_secs":709.574,"ts":"2024-07-26T16:21:19.574Z"},{"side":"blue","kill_num":5,"t_secs":879.882,"ts":"2024-07-26T16:24:09.882Z"},{"side":"blue","kill_num":6,"t_secs":879.882,"ts":"2024-07-26T16:24:09.882Z"},{"side":"blue","kill_num":7,"t_secs":879.882,"ts":"2024-07-26T16:24:09.882Z"},{"side":"red","kill_num":2,"t_secs":879.882,"ts":"2024-07-26T16:24:09.882Z"},{"side":"red","kill_num":3,"t_secs":879.882,"ts":"2024-07-26T16:24:09.882Z"},{"side":"blue","kill_num":8,"t_secs":919.992,"ts":"2024-07-26T16:24:49.992Z"},{"side":"red","kill_num":4,"t_secs":1039.349,"ts":"2024-07-26T16:26:49.349Z"},{"side":"red","kill_num":5,"t_secs":1169.355,"ts":"2024-07-26T16:28:59.355Z"},{"side":"blue","kill_num":9,"t_secs":1189.357,"ts":"2024-07-26T16:29:19.357Z"},{"side":"red","kill_num":6,"t_secs":1189.357,"ts":"2024-07-26T16:29:19.357Z"},{"side":"blue","kill_num":10,"t_secs":1299.922,"ts":"2024-07-26T16:31:09.922Z"},{"side":"blue","kill_num":11,"t_secs":1309.513,"ts":"2024-07-26T16:31:19.513Z"},{"side":"blue","kill_num":12,"t_secs":1409.661,"ts":"2024-07-26T16:32:59.661Z"},{"side":"blue","kill_num":13,"t_secs":1479.876,"ts":"2024-07-26T16:34:09.876Z"},{"side":"blue","kill_num":14,"t_secs":1479.876,"ts":"2024-07-26T16:34:09.876Z"},{"side":"blue","kill_num":15,"t_secs":1489.348,"ts":"2024-07-26T16:34:19.348Z"},{"side":"blue","kill_num":16,"t_secs":1489.348,"ts":"2024-07-26T16:34:19.348Z"},{"side":"red","kill_num":7,"t_secs":1489.348,"ts":"2024-07-26T16:34:19.348Z"},{"side":"blue","kill_num":17,"t_secs":1519.655,"ts":"2024-07-26T16:34:49.655Z"}]}