{"game_id":"112452930845780066","match_id":"112452930845780065","league":"CBLOL","start_time":"2024-06-02T18:00:00Z","blue_team":"PAIN","red_team":"FX","summary":{"blue_total_kills":16,"red_total_kills":20,"blue_time_to_5":14.987766666666666,"red_time_to_5":15.164666666666667,"blue_kills_at_10min":2,"red_kills_at_10min":1,"blue_kills_at_15min":6,"red_kills_at_15min":3,"first_to_five":"blue"},"kills":[{"side":"blue","kill_num":1,"t_secs":229.059,"ts":"2024-06-02T18:15:49.059Z"},{"side":"blue","kill_num":2,"t_secs":429.928,"ts":"2024-06-02T18:19:09.928Z"},{"side":"red","kill_num":1,"t_secs":459.96,"ts":"2024-06-02T18:19:39.960Z"},{"side":"blue","kill_num":3,"t_secs":789.306,"ts":"2024-06-02T18:25:09.306Z"},{"side":"red","kill_num":2,"t_secs":789.306,"ts":"2024-06-02T18:25:09.306Z"},{"side":"red","kill_num":3,"t_secs":859.983,"ts":"2024-06-02T18:26:19.983Z"},{"side":"blue","kill_num":4,"t_secs":879.85,"ts":"2024-06-02T18:26:39.850Z"},{"side":"blue","kill_num":5,"t_secs":899.266,"ts":"2024-06-02T18:26:59.266Z"},{"side":"blue","kill_num":6,"t_secs":899.266,"ts":"2024-06-02T18:26:59.266Z"},{"side":"red","kill_num":4,"t_secs":909.88,"ts":"2024-06-02T18:27:09.880Z"},{"side":"red","kill_num":5,"t_secs":909.88,"ts":"2024-06-02T18:27:09.880Z"},{"side":"red","kill_num":6,"t_secs":949.594,"ts":"2024-06-02T18:27:49.594Z"},{"side":"blue","kill_num":7,"t_secs":959.688,"ts":"2024-06-02T18:27:59.688Z"},{"side":"blue","kill_num":8,"t_secs":969.783,"ts":"2024-06-02T18:28:09.783Z"},{"side":"red","kill_num":7,"t_secs":1029.608,"ts":"2024-06-02T18:29:09.608Z"},{"side":"red","kill_num":8,"t_secs":1039.525,"ts":"2024-06-02T18:29:19.525Z"},{"side":"blue","kill_num":9,"t_secs":1219.632,"ts":"2024-06-02T18:32:19.632Z"},{"side":"blue","kill_num":10,"t_secs":1229.9,"ts":"2024-06-02T18:32:29.900Z"},{"side":"blue","kill_num":11,"t_secs":1239.843,"ts":"2024-06-02T18:32:39.843Z"},{"side":"red","kill_num":9,"t_secs":1239.843,"ts":"2024-06-02T18:32:39.843Z"},{"side":"red","kill_num":10,"t_secs":1239.843,"ts":"2024-06-02T18:32:39.843Z"},{"side":"red","kill_num":11,"t_secs":1249.09,"ts":"2024-06-02T18:32:49.090Z"},{"side":"red","kill_num":12,"t_secs":1349.684,"ts":"2024-06-02T18:34:29.684Z"},{"side":"red","kill_num":13,"t_secs":1429.81,"ts":"2024-06-02T18:35:49.810Z"},{"side":"red","kill_num":14,"t_secs":1459.093,"ts":"2024-06-02T18:36:19.093Z"},{"side":"red","kill_num":15,"t_secs":1459.093,"ts":"2024-06-02T18:36:19.093Z"},{"side":"red","kill_num":16,"t_secs":1469.458,"ts":"2024-06-02T18:36:29.458Z"},{"side":"blue","kill_num":12,"t_secs":1669.084,"ts":"2024-06-02T18:39:49.084Z"},{"side":"blue","kill_num":13,"t_secs":1669.084,"ts":"2024-06-02T18:39:49.084Z"},{"side":"red","kill_num":17,"t_secs":1849.769,"ts":"2024-06-02T18:42:49.769Z"},{"side":"red","kill_num":18,"t_secs":1849.769,"ts":"2024-06-02T18:42:49.769Z"},{"side":"blue","kill_num":14,"t_secs":1999.428,"ts":"2024-06-02T18:45:19.428Z"},{"side":"blue","kill_num":15,"t_secs":1999.428,"ts":"2024-06-02T18:45:19.428Z"},{"side":"red","kill_num":19,"t_secs":1999.428,"ts":"2024-06-02T18:45:19.428Z"},{"side":"blue","kill_num":16,"t_secs":2239.656,"ts":"2024-06-02T18:49:19.656Z"},{"side":"red","kill_num":20,"t_secs":2239.656,"ts":"2024-06-02T18:49:19.656Z"}]}