{"game_id":"112449598160866644","match_id":"112449598160866642","league":"LPL","start_time":"2024-07-19T09:00:00Z","blue_team":"LGD","red_team":"FPX","summary":{"blue_total_kills":20,"red_total_kills":20,"blue_time_to_5":15.16505,"red_time_to_5":20.831799999999998,"blue_kills_at_10min":1,"red_kills_at_10min":1,"blue_kills_at_15min":4,"red_kills_at_15min":3,"first_to_five":"blue"},"kills":[{"side":"red","kill_num":1,"t_secs":409.978,"ts":"2024-07-19T10:34:49.978Z"},{"side":"blue","kill_num":1,"t_secs":599.959,"ts":"2024-07-19T10:37:59.959Z"},{"side":"blue","kill_num":2,"t_secs":719.983,"ts":"2024-07-19T10:39:59.983Z"},{"side":"red","kill_num":2,"t_secs":719.983,"ts":"2024-07-19T10:39:59.983Z"},{"side":"red","kill_num":3,"t_secs":729.895,"ts":"2024-07-19T10:40:09.895Z"},{"side":"blue","kill_num":3,"t_secs":869.956,"ts":"2024-07-19T10:42:29.956Z"},{"side":"blue","kill_num":4,"t_secs":879.963,"ts":"2024-07-19T10:42:39.963Z"},{"side":"blue","kill_num":5,"t_secs":909.903,"ts":"2024-07-19T10:43:09.903Z"},{"side":"red","kill_num":4,"t_secs":1239.912,"ts":"2024-07-19T10:48:39.912Z"},{"side":"blue","kill_num":6,"t_secs":1249.908,"ts":"2024-07-19T10:48:49.908Z"},{"side":"red","kill_num":5,"t_secs":1249.908,"ts":"2024-07-19T10:48:49.908Z"},{"side":"blue","kill_num":7,"t_secs":1289.903,"ts":"2024-07-19T10:49:29.903Z"},{"side":"blue","kill_num":8,"t_secs":1289.903,"ts":"2024-07-19T10:49:29.903Z"},{"side":"blue","kill_num":9,"t_secs":1289.903,"ts":"2024-07-19T10:49:29.903Z"},{"side":"red","kill_num":6,"t_secs":1289.903,"ts":"2024-07-19T10:49:29.903Z"},{"side":"red","kill_num":7,"t_secs":1479.945,"ts":"2024-07-19T10:52:39.945Z"},{"side":"blue","kill_num":10,"t_secs":1489.999,"ts":"2024-07-19T10:52:49.999Z"},{"side":"red","kill_num":8,"t_secs":1489.999,"ts":"2024-07-19T10:52:49.999Z"},{"side":"red","kill_num":9,"t_secs":1489.999,"ts":"2024-07-19T10:52:49.999Z"},{"side":"red","kill_num":10,"t_secs":1489.999,"ts":"2024-07-19T10:52:49.999Z"},{"side":"red","kill_num":11,"t_secs":1499.904,"ts":"2024-07-19T10:52:59.904Z"},{"side":"blue","kill_num":11,"t_secs":1619.904,"ts":"2024-07-19T10:54:59.904Z"},{"side":"blue","kill_num":12,"t_secs":1809.962,"ts":"2024-07-19T10:58:09.962Z"},{"side":"red","kill_num":12,"t_secs":1819.911,"ts":"2024-07-19T10:58:19.911Z"},{"side":"blue","kill_num":13,"t_secs":1829.917,"ts":"2024-07-19T10:58:29.917Z"},{"side":"red","kill_num":13,"t_secs":1829.917,"ts":"2024-07-19T10:58:29.917Z"},{"side":"blue","kill_num":14,"t_secs":1869.888,"ts":"2024-07-19T10:59:09.888Z"},{"side":"blue","kill_num":15,"t_secs":1869.888,"ts":"2024-07-19T10:59:09.888Z"},{"side":"red","kill_num":14,"t_secs":1869.888,"ts":"2024-07-19T10:59:09.888Z"},{"side":"red","kill_num":15,"t_secs":1869.888,"ts":"2024-07-19T10:59:09.888Z"},{"side":"red","kill_num":16,"t_secs":1879.908,"ts":"2024-07-19T10:59:19.908Z"},{"side":"red","kill_num":17,"t_secs":1909.911,"ts":"2024-07-19T10:59:49.911Z"},{"side":"red","kill_num":18,"t_secs":1999.893,"ts":"2024-07-19T11:01:19.893Z"},{"side":"blue","kill_num":16,"t_secs":2139.887,"ts":"2024-07-19T11:03:39.887Z"},{"side":"blue","kill_num":17,"t_secs":2149.891,"ts":"2024-07-19T11:03:49.891Z"},{"side":"red","kill_num":19,"t_secs":2149.891,"ts":"2024-07-19T11:03:49.891Z"},{"side":"red","kill_num":20,"t_secs":2149.891,"ts":"2024-07-19T11:03:49.891Z"},{"side":"blue","kill_num":18,"t_secs":2159.9,"ts":"2024-07-19T11:03:59.900Z"},{"side":"blue","kill_num":19,"t_secs":2159.9,"ts":"2024-07-19T11:03:59.900Z"},{"side":"blue","kill_num":20,"t_secs":2219.913,"ts":"2024-07-19T11:04:59.913Z"}]}