{"game_id":"112452930845845728","match_id":"112452930845845727","league":"CBLOL","start_time":"2024-07-12T17:00:00Z","blue_team":"FUR","red_team":"VKS","summary":{"blue_total_kills":10,"red_total_kills":24,"blue_time_to_5":16.821066666666667,"red_time_to_5":14.66295,"blue_kills_at_10min":1,"red_kills_at_10min":1,"blue_kills_at_15min":3,"red_kills_at_15min":5,"first_to_five":"red"},"kills":[{"side":"blue","kill_num":1,"t_secs":249.916,"ts":"2024-07-12T17:07:39.916Z"},{"side":"red","kill_num":1,"t_secs":259.789,"ts":"2024-07-12T17:07:49.789Z"},{"side":"red","kill_num":2,"t_secs":649.609,"ts":"2024-07-12T17:14:19.609Z"},{"side":"blue","kill_num":2,"t_secs":679.283,"ts":"2024-07-12T17:14:49.283Z"},{"side":"blue","kill_num":3,"t_secs":679.283,"ts":"2024-07-12T17:14:49.283Z"},{"side":"red","kill_num":3,"t_secs":869.264,"ts":"2024-07-12T17:17:59.264Z"},{"side":"red","kill_num":4,"t_secs":879.777,"ts":"2024-07-12T17:18:09.777Z"},{"side":"red","kill_num":5,"t_secs":879.777,"ts":"2024-07-12T17:18:09.777Z"},{"side":"blue","kill_num":4,"t_secs":989.291,"ts":"2024-07-12T17:19:59.291Z"},{"side":"red","kill_num":6,"t_secs":999.945,"ts":"2024-07-12T17:20:09.945Z"},{"side":"blue","kill_num":5,"t_secs":1009.264,"ts":"2024-07-12T17:20:19.264Z"},{"side":"red","kill_num":7,"t_secs":1009.264,"ts":"2024-07-12T17:20:19.264Z"},{"side":"blue","kill_num":6,"t_secs":1039.769,"ts":"2024-07-12T17:20:49.769Z"},{"side":"blue","kill_num":7,"t_secs":1109.71,"ts":"2024-07-12T17:21:59.710Z"},{"side":"red","kill_num":8,"t_secs":1109.71,"ts":"2024-07-12T17:21:59.710Z"},{"side":"red","kill_num":9,"t_secs":1119.938,"ts":"2024-07-12T17:22:09.938Z"},{"side":"red","kill_num":10,"t_secs":1129.907,"ts":"2024-07-12T17:22:19.907Z"},{"side":"red","kill_num":11,"t_secs":1299.279,"ts":"2024-07-12T17:25:09.279Z"},{"side":"red","kill_num":12,"t_secs":1329.838,"ts":"2024-07-12T17:25:39.838Z"},{"side":"red","kill_num":13,"t_secs":1329.838,"ts":"2024-07-12T17:25:39.838Z"},{"side":"blue","kill_num":8,"t_secs":1339.745,"ts":"2024-07-12T17:25:49.745Z"},{"side":"red","kill_num":14,"t_secs":1339.745,"ts":"2024-07-12T17:25:49.745Z"},{"side":"red","kill_num":15,"t_secs":1419.924,"ts":"2024-07-12T17:27:09.924Z"},{"side":"red","kill_num":16,"t_secs":1429.986,"ts":"2024-07-12T17:27:19.986Z"},{"side":"red","kill_num":17,"t_secs":1429.986,"ts":"2024-07-12T17:27:19.986Z"},{"side":"blue","kill_num":9,"t_secs":1509.857,"ts":"2024-07-12T17:28:39.857Z"},{"side":"red","kill_num":18,"t_secs":1509.857,"ts":"2024-07-12T17:28:39.857Z"},{"side":"blue","kill_num":10,"t_secs":1519.965,"ts":"2024-07-12T17:28:49.965Z"},{"side":"red","kill_num":19,"t_secs":1519.965,"ts":"2024-07-12T17:28:49.965Z"},{"side":"red","kill_num":20,"t_secs":1609.859,"ts":"2024-07-12T17:30:19.859Z"},{"side":"red","kill_num":21,"t_secs":1609.859,"ts":"2024-07-12T17:30:19.859Z"},{"side":"red","kill_num":22,"t_secs":1619.397,"ts":"2024-07-12T17:30:29.397Z"},{"side":"red","kill_num":23,"t_secs":1619.397,"ts":"2024-07-12T17:30:29.397Z"},{"side":"red","kill_num":24,"t_secs":1649.268,"ts":"2024-07-12T17:30:59.268Z"}]}