{"game_id":"112966669924194824","match_id":"112966669924194821","league":"Worlds","start_time":"2024-10-12T15:00:00Z","blue_team":"TLAW","red_team":"GAM","summary":{"blue_total_kills":6,"red_total_kills":18,"blue_time_to_5":18.496716666666668,"red_time_to_5":16.663333333333334,"blue_kills_at_10min":2,"red_kills_at_10min":3,"blue_kills_at_15min":2,"red_kills_at_15min":4,"first_to_five":"red"},"kills":[{"side":"red","kill_num":1,"t_secs":149.79,"ts":"2024-10-12T16:25:59.790Z"},{"side":"red","kill_num":2,"t_secs":279.931,"ts":"2024-10-12T16:28:09.931Z"},{"side":"blue","kill_num":1,"t_secs":439.79,"ts":"2024-10-12T16:30:49.790Z"},{"side":"blue","kill_num":2,"t_secs":449.791,"ts":"2024-10-12T16:30:59.791Z"},{"side":"red","kill_num":3,"t_secs":449.791,"ts":"2024-10-12T16:30:59.791Z"},{"side":"red","kill_num":4,"t_secs":659.973,"ts":"2024-10-12T16:34:29.973Z"},{"side":"red","kill_num":5,"t_secs":999.8,"ts":"2024-10-12T16:40:09.800Z"},{"side":"red","kill_num":6,"t_secs":1009.984,"ts":"2024-10-12T16:40:19.984Z"},{"side":"blue","kill_num":3,"t_secs":1019.88,"ts":"2024-10-12T16:40:29.880Z"},{"side":"blue","kill_num":4,"t_secs":1109.803,"ts":"2024-10-12T16:41:59.803Z"},{"side":"blue","kill_num":5,"t_secs":1109.803,"ts":"2024-10-12T16:41:59.803Z"},{"side":"red","kill_num":7,"t_secs":1109.803,"ts":"2024-10-12T16:41:59.803Z"},{"side":"red","kill_num":8,"t_secs":1109.803,"ts":"2024-10-12T16:41:59.803Z"},{"side":"red","kill_num":9,"t_secs":1209.966,"ts":"2024-10-12T16:43:39.966Z"},{"side":"red","kill_num":10,"t_secs":1329.803,"ts":"2024-10-12T16:45:39.803Z"},{"side":"blue","kill_num":6,"t_secs":1369.999,"ts":"2024-10-12T16:46:19.999Z"},{"side":"red","kill_num":11,"t_secs":1369.999,"ts":"2024-10-12T16:46:19.999Z"},{"side":"red","kill_num":12,"t_secs":1379.924,"ts":"2024-10-12T16:46:29.924Z"},{"side":"red","kill_num":13,"t_secs":1519.975,"ts":"2024-10-12T16:48:49.975Z"},{"side":"red","kill_num":14,"t_secs":1529.944,"ts":"2024-10-12T16:48:59.944Z"},{"side":"red","kill_num":15,"t_secs":1529.944,"ts":"2024-10-12T16:48:59.944Z"},{"side":"red","kill_num":16,"t_secs":1699.812,"ts":"2024-10-12T16:51:49.812Z"},{"side":"red","kill_num":17,"t_secs":1709.817,"ts":"2024-10-12T16:51:59.817Z"},{"side":"red","kill_num":18,"t_secs":1719.817,"ts":"2024-10-12T16:52:09.817Z"}]}