{"game_id":"112966669924194818","match_id":"112966669924194817","league":"Worlds","start_time":"2024-10-10T15:00:00Z","blue_team":"HLE","red_team":"FLY","summary":{"blue_total_kills":16,"red_total_kills":12,"blue_time_to_5":10.331983333333334,"red_time_to_5":22.998383333333333,"blue_kills_at_10min":3,"red_kills_at_10min":0,"blue_kills_at_15min":5,"red_kills_at_15min":1,"first_to_five":"blue"},"kills":[{"side":"blue","kill_num":1,"t_secs":179.755,"ts":"2024-10-10T14:12:19.755Z"},{"side":"blue","kill_num":2,"t_secs":399.548,"ts":"2024-10-10T14:15:59.548Z"},{"side":"blue","kill_num":3,"t_secs":569.802,"ts":"2024-10-10T14:18:49.802Z"},{"side":"blue","kill_num":4,"t_secs":609.74,"ts":"2024-10-10T14:19:29.740Z"},{"side":"blue","kill_num":5,"t_secs":619.919,"ts":"2024-10-10T14:19:39.919Z"},{"side":"red","kill_num":1,"t_secs":619.919,"ts":"2024-10-10T14:19:39.919Z"},{"side":"red","kill_num":2,"t_secs":1039.55,"ts":"2024-10-10T14:26:39.550Z"},{"side":"blue","kill_num":6,"t_secs":1059.92,"ts":"2024-10-10T14:26:59.920Z"},{"side":"blue","kill_num":7,"t_secs":1119.828,"ts":"2024-10-10T14:27:59.828Z"},{"side":"blue","kill_num":8,"t_secs":1129.992,"ts":"2024-10-10T14:28:09.992Z"},{"side":"red","kill_num":3,"t_secs":1369.825,"ts":"2024-10-10T14:32:09.825Z"},{"side":"red","kill_num":4,"t_secs":1369.825,"ts":"2024-10-10T14:32:09.825Z"},{"side":"red","kill_num":5,"t_secs":1379.903,"ts":"2024-10-10T14:32:19.903Z"},{"side":"red","kill_num":6,"t_secs":1379.903,"ts":"2024-10-10T14:32:19.903Z"},{"side":"blue","kill_num":9,"t_secs":1449.828,"ts":"2024-10-10T14:33:29.828Z"},{"side":"red","kill_num":7,"t_secs":1619.689,"ts":"2024-10-10T14:36:19.689Z"},{"side":"red","kill_num":8,"t_secs":1629.918,"ts":"2024-10-10T14:36:29.918Z"},{"side":"blue","kill_num":10,"t_secs":1649.788,"ts":"2024-10-10T14:36:49.788Z"},{"side":"blue","kill_num":11,"t_secs":1659.567,"ts":"2024-10-10T14:36:59.567Z"},{"side":"red","kill_num":9,"t_secs":1729.937,"ts":"2024-10-10T14:38:09.937Z"},{"side":"red","kill_num":10,"t_secs":1739.912,"ts":"2024-10-10T14:38:19.912Z"},{"side":"red","kill_num":11,"t_secs":1749.983,"ts":"2024-10-10T14:38:29.983Z"},{"side":"red","kill_num":12,"t_secs":1819.96,"ts":"2024-10-10T14:39:39.960Z"},{"side":"blue","kill_num":12,"t_secs":1979.995,"ts":"2024-10-10T14:42:19.995Z"},{"side":"blue","kill_num":13,"t_secs":1979.995,"ts":"2024-10-10T14:42:19.995Z"},{"side":"blue","kill_num":14,"t_secs":1989.56,"ts":"2024-10-10T14:42:29.560Z"},{"side":"blue","kill_num":15,"t_secs":1989.56,"ts":"2024-10-10T14:42:29.560Z"},{"side":"blue","kill_num":16,"t_secs":1989.56,"ts":"2024-10-10T14:42:29.560Z"}]}