{"game_id":"113487543463874905","match_id":"113487543463874904","league":"LEC","start_time":"2025-08-18T17:00:00Z","blue_team":"G2","red_team":"SHFT","summary":{"blue_total_kills":18,"red_total_kills":9,"blue_time_to_5":27.16285,"red_time_to_5":17.998316666666664,"blue_kills_at_10min":0,"red_kills_at_10min":2,"blue_kills_at_15min":2,"red_kills_at_15min":3,"first_to_five":"red"},"kills":[{"side":"red","kill_num":1,"t_secs":239.778,"ts":"2025-08-18T17:55:49.778Z"},{"side":"red","kill_num":2,"t_secs":389.794,"ts":"2025-08-18T17:58:19.794Z"},{"side":"blue","kill_num":1,"t_secs":729.942,"ts":"2025-08-18T18:03:59.942Z"},{"side":"red","kill_num":3,"t_secs":729.942,"ts":"2025-08-18T18:03:59.942Z"},{"side":"blue","kill_num":2,"t_secs":789.779,"ts":"2025-08-18T18:04:59.779Z"},{"side":"red","kill_num":4,"t_secs":959.943,"ts":"2025-08-18T18:07:49.943Z"},{"side":"red","kill_num":5,"t_secs":1079.899,"ts":"2025-08-18T18:09:49.899Z"},{"side":"red","kill_num":6,"t_secs":1089.782,"ts":"2025-08-18T18:09:59.782Z"},{"side":"blue","kill_num":3,"t_secs":1099.766,"ts":"2025-08-18T18:10:09.766Z"},{"side":"red","kill_num":7,"t_secs":1169.9,"ts":"2025-08-18T18:11:19.900Z"},{"side":"blue","kill_num":4,"t_secs":1269.782,"ts":"2025-08-18T18:12:59.782Z"},{"side":"blue","kill_num":5,"t_secs":1629.771,"ts":"2025-08-18T18:18:59.771Z"},{"side":"blue","kill_num":6,"t_secs":1799.88,"ts":"2025-08-18T18:21:49.880Z"},{"side":"blue","kill_num":7,"t_secs":1799.88,"ts":"2025-08-18T18:21:49.880Z"},{"side":"blue","kill_num":8,"t_secs":1799.88,"ts":"2025-08-18T18:21:49.880Z"},{"side":"blue","kill_num":9,"t_secs":1879.79,"ts":"2025-08-18T18:23:09.790Z"},{"side":"blue","kill_num":10,"t_secs":1939.77,"ts":"2025-08-18T18:24:09.770Z"},{"side":"blue","kill_num":11,"t_secs":1999.987,"ts":"2025-08-18T18:25:09.987Z"},{"side":"red","kill_num":8,"t_secs":1999.987,"ts":"2025-08-18T18:25:09.987Z"},{"side":"blue","kill_num":12,"t_secs":2009.803,"ts":"2025-08-18T18:25:19.803Z"},{"side":"blue","kill_num":13,"t_secs":2049.964,"ts":"2025-08-18T18:25:59.964Z"},{"side":"blue","kill_num":14,"t_secs":2079.785,"ts":"2025-08-18T18:26:29.785Z"},{"side":"blue","kill_num":15,"t_secs":2179.789,"ts":"2025-08-18T18:28:09.789Z"},{"side":"blue","kill_num":16,"t_secs":2189.774,"ts":"2025-08-18T18:28:19.774Z"},{"side":"blue","kill_num":17,"t_secs":2199.992,"ts":"2025-08-18T18:28:29.992Z"},{"side":"blue","kill_num":18,"t_secs":2219.762,"ts":"2025-08-18T18:28:49.762Z"},{"side":"red","kill_num":9,"t_secs":2219.762,"ts":"2025-08-18T18:28:49.762Z"}]}