{"game_id":"113487475359325319","match_id":"113487475359325317","league":"LEC","start_time":"2025-04-26T13:00:00Z","blue_team":"GX","red_team":"G2","summary":{"blue_total_kills":6,"red_total_kills":16,"blue_time_to_5":18.33155,"red_time_to_5":25.32091666666667,"blue_kills_at_10min":0,"red_kills_at_10min":0,"blue_kills_at_15min":1,"red_kills_at_15min":1,"first_to_five":"blue"},"kills":[{"side":"red","kill_num":1,"t_secs":749.33,"ts":"2025-04-26T14:41:09.330Z"},{"side":"blue","kill_num":1,"t_secs":849.718,"ts":"2025-04-26T14:42:49.718Z"},{"side":"blue","kill_num":2,"t_secs":1019.662,"ts":"2025-04-26T14:45:39.662Z"},{"side":"blue","kill_num":3,"t_secs":1029.99,"ts":"2025-04-26T14:45:49.990Z"},{"side":"blue","kill_num":4,"t_secs":1039.913,"ts":"2025-04-26T14:45:59.913Z"},{"side":"blue","kill_num":5,"t_secs":1099.893,"ts":"2025-04-26T14:46:59.893Z"},{"side":"red","kill_num":2,"t_secs":1299.781,"ts":"2025-04-26T14:50:19.781Z"},{"side":"red","kill_num":3,"t_secs":1299.781,"ts":"2025-04-26T14:50:19.781Z"},{"side":"red","kill_num":4,"t_secs":1309.873,"ts":"2025-04-26T14:50:29.873Z"},{"side":"blue","kill_num":6,"t_secs":1389.696,"ts":"2025-04-26T14:51:49.696Z"},{"side":"red","kill_num":5,"t_secs":1519.255,"ts":"2025-04-26T14:53:59.255Z"},{"side":"red","kill_num":6,"t_secs":1519.255,"ts":"2025-04-26T14:53:59.255Z"},{"side":"red","kill_num":7,"t_secs":1629.812,"ts":"2025-04-26T14:55:49.812Z"},{"side":"red","kill_num":8,"t_secs":1639.492,"ts":"2025-04-26T14:55:59.492Z"},{"side":"red","kill_num":9,"t_secs":1639.492,"ts":"2025-04-26T14:55:59.492Z"},{"side":"red","kill_num":10,"t_secs":1639.492,"ts":"2025-04-26T14:55:59.492Z"},{"side":"red","kill_num":11,"t_secs":1649.714,"ts":"2025-04-26T14:56:09.714Z"},{"side":"red","kill_num":12,"t_secs":1829.976,"ts":"2025-04-26T14:59:09.976Z"},{"side":"red","kill_num":13,"t_secs":1839.169,"ts":"2025-04-26T14:59:19.169Z"},{"side":"red","kill_num":14,"t_secs":1839.169,"ts":"2025-04-26T14:59:19.169Z"},{"side":"red","kill_num":15,"t_secs":1859.359,"ts":"2025-04-26T14:59:39.359Z"},{"side":"red","kill_num":16,"t_secs":1869.261,"ts":"2025-04-26T14:59:49.261Z"}]}