{"game_id":"113990318291619949","match_id":"113990318291619947","league":"EMEA Masters","start_time":"2025-03-17T16:00:00Z","blue_team":"SUP","red_team":"Z10","summary":{"blue_total_kills":10,"red_total_kills":43,"blue_time_to_5":17.165733333333332,"red_time_to_5":7.997683333333333,"blue_kills_at_10min":2,"red_kills_at_10min":7,"blue_kills_at_15min":3,"red_kills_at_15min":13,"first_to_five":"red"},"kills":[{"side":"red","kill_num":1,"t_secs":169.74,"ts":"2025-03-17T17:00:39.740Z"},{"side":"red","kill_num":2,"t_secs":329.975,"ts":"2025-03-17T17:03:19.975Z"},{"side":"red","kill_num":3,"t_secs":439.871,"ts":"2025-03-17T17:05:09.871Z"},{"side":"red","kill_num":4,"t_secs":459.551,"ts":"2025-03-17T17:05:29.551Z"},{"side":"blue","kill_num":1,"t_secs":469.807,"ts":"2025-03-17T17:05:39.807Z"},{"side":"red","kill_num":5,"t_secs":479.861,"ts":"2025-03-17T17:05:49.861Z"},{"side":"red","kill_num":6,"t_secs":519.815,"ts":"2025-03-17T17:06:29.815Z"},{"side":"red","kill_num":7,"t_secs":569.573,"ts":"2025-03-17T17:07:19.573Z"},{"side":"blue","kill_num":2,"t_secs":599.564,"ts":"2025-03-17T17:07:49.564Z"},{"side":"red","kill_num":8,"t_secs":669.794,"ts":"2025-03-17T17:08:59.794Z"},{"side":"blue","kill_num":3,"t_secs":679.568,"ts":"2025-03-17T17:09:09.568Z"},{"side":"red","kill_num":9,"t_secs":679.568,"ts":"2025-03-17T17:09:09.568Z"},{"side":"red","kill_num":10,"t_secs":839.818,"ts":"2025-03-17T17:11:49.818Z"},{"side":"red","kill_num":11,"t_secs":849.974,"ts":"2025-03-17T17:11:59.974Z"},{"side":"red","kill_num":12,"t_secs":849.974,"ts":"2025-03-17T17:11:59.974Z"},{"side":"red","kill_num":13,"t_secs":869.995,"ts":"2025-03-17T17:12:19.995Z"},{"side":"red","kill_num":14,"t_secs":929.744,"ts":"2025-03-17T17:13:19.744Z"},{"side":"blue","kill_num":4,"t_secs":999.902,"ts":"2025-03-17T17:14:29.902Z"},{"side":"red","kill_num":15,"t_secs":1009.86,"ts":"2025-03-17T17:14:39.860Z"},{"side":"red","kill_num":16,"t_secs":1019.961,"ts":"2025-03-17T17:14:49.961Z"},{"side":"red","kill_num":17,"t_secs":1019.961,"ts":"2025-03-17T17:14:49.961Z"},{"side":"blue","kill_num":5,"t_secs":1029.944,"ts":"2025-03-17T17:14:59.944Z"},{"side":"red","kill_num":18,"t_secs":1029.944,"ts":"2025-03-17T17:14:59.944Z"},{"side":"red","kill_num":19,"t_secs":1039.549,"ts":"2025-03-17T17:15:09.549Z"},{"side":"red","kill_num":20,"t_secs":1129.834,"ts":"2025-03-17T17:16:39.834Z"},{"side":"red","kill_num":21,"t_secs":1139.581,"ts":"2025-03-17T17:16:49.581Z"},{"side":"red","kill_num":22,"t_secs":1139.581,"ts":"2025-03-17T17:16:49.581Z"},{"side":"red","kill_num":23,"t_secs":1159.811,"ts":"2025-03-17T17:17:09.811Z"},{"side":"red","kill_num":24,"t_secs":1199.571,"ts":"2025-03-17T17:17:49.571Z"},{"side":"red","kill_num":25,"t_secs":1209.789,"ts":"2025-03-17T17:17:59.789Z"},{"side":"red","kill_num":26,"t_secs":1219.573,"ts":"2025-03-17T17:18:09.573Z"},{"side":"red","kill_num":27,"t_secs":1229.807,"ts":"2025-03-17T17:18:19.807Z"},{"side":"blue","kill_num":6,"t_secs":1269.565,"ts":"2025-03-17T17:18:59.565Z"},{"side":"blue","kill_num":7,"t_secs":1279.825,"ts":"2025-03-17T17:19:09.825Z"},{"side":"red","kill_num":28,"t_secs":1279.825,"ts":"2025-03-17T17:19:09.825Z"},{"side":"blue","kill_num":8,"t_secs":1289.925,"ts":"2025-03-17T17:19:19.925Z"},{"side":"red","kill_num":29,"t_secs":1289.925,"ts":"2025-03-17T17:19:19.925Z"},{"side":"red","kill_num":30,"t_secs":1289.925,"ts":"2025-03-17T17:19:19.925Z"},{"side":"blue","kill_num":9,"t_secs":1359.964,"ts":"2025-03-17T17:20:29.964Z"},{"side":"red","kill_num":31,"t_secs":1369.963,"ts":"2025-03-17T17:20:39.963Z"},{"side":"red","kill_num":32,"t_secs":1369.963,"ts":"2025-03-17T17:20:39.963Z"},{"side":"red","kill_num":33,"t_secs":1379.554,"ts":"2025-03-17T17:20:49.554Z"},{"side":"red","kill_num":34,"t_secs":1389.578,"ts":"2025-03-17T17:20:59.578Z"},{"side":"red","kill_num":35,"t_secs":1439.58,"ts":"2025-03-17T17:21:49.580Z"},{"side":"red","kill_num":36,"t_secs":1439.58,"ts":"2025-03-17T17:21:49.580Z"},{"side":"red","kill_num":37,"t_secs":1449.597,"ts":"2025-03-17T17:21:59.597Z"},{"side":"red","kill_num":38,"t_secs":1489.943,"ts":"2025-03-17T17:22:39.943Z"},{"side":"blue","kill_num":10,"t_secs":1499.954,"ts":"2025-03-17T17:22:49.954Z"},{"side":"red","kill_num":39,"t_secs":1499.954,"ts":"2025-03-17T17:22:49.954Z"},{"side":"red","kill_num":40,"t_secs":1499.954,"ts":"2025-03-17T17:22:49.954Z"},{"side":"red","kill_num":41,"t_secs":1499.954,"ts":"2025-03-17T17:22:49.954Z"},{"side":"red","kill_num":42,"t_secs":1499.954,"ts":"2025-03-17T17:22:49.954Z"},{"side":"red","kill_num":43,"t_secs":1529.549,"ts":"2025-03-17T17:23:19.549Z"}]}