{"game_id":"114755484277865745","match_id":"114755484277865744","league":"La Ligue Fran\u00e7aise","start_time":"2025-07-24T19:00:00Z","blue_team":"KCB","red_team":"SLY","summary":{"blue_total_kills":15,"red_total_kills":7,"truncated":true,"early_stop_kills":10,"blue_time_to_5":22.829333333333334,"red_time_to_5":22.829333333333334,"blue_time_to_10":30.82923333333333,"red_time_to_10":null,"blue_kills_at_10min":1,"red_kills_at_10min":0,"blue_kills_at_15min":1,"red_kills_at_15min":1,"first_to_five":"red"},"kills":[{"side":"blue","kill_num":1,"t_secs":489.762,"ts":"2025-07-24T18:59:39.762Z"},{"side":"red","kill_num":1,"t_secs":649.905,"ts":"2025-07-24T19:02:19.905Z"},{"side":"red","kill_num":2,"t_secs":989.772,"ts":"2025-07-24T19:07:59.772Z"},{"side":"red","kill_num":3,"t_secs":1039.763,"ts":"2025-07-24T19:08:49.763Z"},{"side":"blue","kill_num":2,"t_secs":1129.778,"ts":"2025-07-24T19:10:19.778Z"},{"side":"blue","kill_num":3,"t_secs":1139.764,"ts":"2025-07-24T19:10:29.764Z"},{"side":"blue","kill_num":4,"t_secs":1369.76,"ts":"2025-07-24T19:14:19.760Z"},{"side":"blue","kill_num":5,"t_secs":1369.76,"ts":"2025-07-24T19:14:19.760Z"},{"side":"blue","kill_num":6,"t_secs":1369.76,"ts":"2025-07-24T19:14:19.760Z"},{"side":"red","kill_num":4,"t_secs":1369.76,"ts":"2025-07-24T19:14:19.760Z"},{"side":"red","kill_num":5,"t_secs":1369.76,"ts":"2025-07-24T19:14:19.760Z"},{"side":"blue","kill_num":7,"t_secs":1619.977,"ts":"2025-07-24T19:18:29.977Z"},{"side":"blue","kill_num":8,"t_secs":1839.759,"ts":"2025-07-24T19:22:09.759Z"},{"side":"blue","kill_num":9,"t_secs":1839.759,"ts":"2025-07-24T19:22:09.759Z"},{"side":"red","kill_num":6,"t_secs":1839.759,"ts":"2025-07-24T19:22:09.759Z"},{"side":"blue","kill_num":10,"t_secs":1849.754,"ts":"2025-07-24T19:22:19.754Z"},{"side":"blue","kill_num":11,"t_secs":1879.938,"ts":"2025-07-24T19:22:49.938Z"},{"side":"red","kill_num":7,"t_secs":1879.938,"ts":"2025-07-24T19:22:49.938Z"},{"side":"blue","kill_num":12,"t_secs":2039.842,"ts":"2025-07-24T19:25:29.842Z"},{"side":"blue","kill_num":13,"t_secs":2049.855,"ts":"2025-07-24T19:25:39.855Z"},{"side":"blue","kill_num":14,"t_secs":2069.966,"ts":"2025-07-24T19:25:59.966Z"},{"side":"blue","kill_num":15,"t_secs":2069.966,"ts":"2025-07-24T19:25:59.966Z"}]}