{"game_id":"115016231910967023","match_id":"115016231910967022","league":"EMEA Masters","start_time":"2025-10-01T15:00:00Z","blue_team":"GL","red_team":"TOG","summary":{"blue_total_kills":23,"red_total_kills":16,"blue_time_to_5":19.166566666666665,"red_time_to_5":22.1615,"blue_kills_at_10min":4,"red_kills_at_10min":1,"blue_kills_at_15min":4,"red_kills_at_15min":2,"first_to_five":"blue"},"kills":[{"side":"blue","kill_num":1,"t_secs":189.406,"ts":"2025-10-01T15:04:09.406Z"},{"side":"blue","kill_num":2,"t_secs":339.999,"ts":"2025-10-01T15:06:39.999Z"},{"side":"red","kill_num":1,"t_secs":359.367,"ts":"2025-10-01T15:06:59.367Z"},{"side":"blue","kill_num":3,"t_secs":459.381,"ts":"2025-10-01T15:08:39.381Z"},{"side":"blue","kill_num":4,"t_secs":529.748,"ts":"2025-10-01T15:09:49.748Z"},{"side":"red","kill_num":2,"t_secs":779.379,"ts":"2025-10-01T15:13:59.379Z"},{"side":"red","kill_num":3,"t_secs":929.727,"ts":"2025-10-01T15:16:29.727Z"},{"side":"blue","kill_num":5,"t_secs":1149.994,"ts":"2025-10-01T15:20:09.994Z"},{"side":"blue","kill_num":6,"t_secs":1329.69,"ts":"2025-10-01T15:23:09.690Z"},{"side":"blue","kill_num":7,"t_secs":1329.69,"ts":"2025-10-01T15:23:09.690Z"},{"side":"red","kill_num":4,"t_secs":1329.69,"ts":"2025-10-01T15:23:09.690Z"},{"side":"red","kill_num":5,"t_secs":1329.69,"ts":"2025-10-01T15:23:09.690Z"},{"side":"red","kill_num":6,"t_secs":1339.975,"ts":"2025-10-01T15:23:19.975Z"},{"side":"red","kill_num":7,"t_secs":1589.998,"ts":"2025-10-01T15:27:29.998Z"},{"side":"red","kill_num":8,"t_secs":1589.998,"ts":"2025-10-01T15:27:29.998Z"},{"side":"blue","kill_num":8,"t_secs":1599.403,"ts":"2025-10-01T15:27:39.403Z"},{"side":"blue","kill_num":9,"t_secs":1599.403,"ts":"2025-10-01T15:27:39.403Z"},{"side":"red","kill_num":9,"t_secs":1599.403,"ts":"2025-10-01T15:27:39.403Z"},{"side":"red","kill_num":10,"t_secs":1609.798,"ts":"2025-10-01T15:27:49.798Z"},{"side":"blue","kill_num":10,"t_secs":1679.888,"ts":"2025-10-01T15:28:59.888Z"},{"side":"blue","kill_num":11,"t_secs":1709.935,"ts":"2025-10-01T15:29:29.935Z"},{"side":"blue","kill_num":12,"t_secs":1739.878,"ts":"2025-10-01T15:29:59.878Z"},{"side":"red","kill_num":11,"t_secs":1869.986,"ts":"2025-10-01T15:32:09.986Z"},{"side":"red","kill_num":12,"t_secs":1879.562,"ts":"2025-10-01T15:32:19.562Z"},{"side":"blue","kill_num":13,"t_secs":1939.461,"ts":"2025-10-01T15:33:19.461Z"},{"side":"blue","kill_num":14,"t_secs":1949.972,"ts":"2025-10-01T15:33:29.972Z"},{"side":"blue","kill_num":15,"t_secs":1989.773,"ts":"2025-10-01T15:34:09.773Z"},{"side":"red","kill_num":13,"t_secs":1989.773,"ts":"2025-10-01T15:34:09.773Z"},{"side":"blue","kill_num":16,"t_secs":1999.972,"ts":"2025-10-01T15:34:19.972Z"},{"side":"red","kill_num":14,"t_secs":2029.399,"ts":"2025-10-01T15:34:49.399Z"},{"side":"blue","kill_num":17,"t_secs":2039.53,"ts":"2025-10-01T15:34:59.530Z"},{"side":"red","kill_num":15,"t_secs":2039.53,"ts":"2025-10-01T15:34:59.530Z"},{"side":"blue","kill_num":18,"t_secs":2209.959,"ts":"2025-10-01T15:37:49.959Z"},{"side":"blue","kill_num":19,"t_secs":2209.959,"ts":"2025-10-01T15:37:49.959Z"},{"side":"blue","kill_num":20,"t_secs":2209.959,"ts":"2025-10-01T15:37:49.959Z"},{"side":"red","kill_num":16,"t_secs":2209.959,"ts":"2025-10-01T15:37:49.959Z"},{"side":"blue","kill_num":21,"t_secs":2219.61,"ts":"2025-10-01T15:37:59.610Z"},{"side":"blue","kill_num":22,"t_secs":2219.61,"ts":"2025-10-01T15:37:59.610Z"},{"side":"blue","kill_num":23,"t_secs":2249.407,"ts":"2025-10-01T15:38:29.407Z"}]}