{"game_id":"115570888977308439","match_id":"115570888977308435","league":"First Stand","start_time":"2026-03-22T13:00:00Z","blue_team":"G2","red_team":"BLG","summary":{"blue_total_kills":8,"red_total_kills":12,"truncated":true,"early_stop_kills":10,"blue_time_to_5":25.985216666666666,"red_time_to_5":11.318633333333334,"blue_time_to_10":null,"red_time_to_10":14.486283333333335,"blue_kills_at_10min":2,"red_kills_at_10min":4,"blue_kills_at_15min":2,"red_kills_at_15min":10,"first_to_five":"red"},"kills":[{"side":"red","kill_num":1,"t_secs":179.989,"ts":"2026-03-22T16:07:39.989Z"},{"side":"blue","kill_num":1,"t_secs":189.576,"ts":"2026-03-22T16:07:49.576Z"},{"side":"blue","kill_num":2,"t_secs":199.764,"ts":"2026-03-22T16:07:59.764Z"},{"side":"red","kill_num":2,"t_secs":449.931,"ts":"2026-03-22T16:12:09.931Z"},{"side":"red","kill_num":3,"t_secs":459.753,"ts":"2026-03-22T16:12:19.753Z"},{"side":"red","kill_num":4,"t_secs":459.753,"ts":"2026-03-22T16:12:19.753Z"},{"side":"red","kill_num":5,"t_secs":679.118,"ts":"2026-03-22T16:15:59.118Z"},{"side":"red","kill_num":6,"t_secs":729.989,"ts":"2026-03-22T16:16:49.989Z"},{"side":"red","kill_num":7,"t_secs":749.729,"ts":"2026-03-22T16:17:09.729Z"},{"side":"red","kill_num":8,"t_secs":849.817,"ts":"2026-03-22T16:18:49.817Z"},{"side":"red","kill_num":9,"t_secs":869.177,"ts":"2026-03-22T16:19:09.177Z"},{"side":"red","kill_num":10,"t_secs":869.177,"ts":"2026-03-22T16:19:09.177Z"},{"side":"blue","kill_num":3,"t_secs":1029.113,"ts":"2026-03-22T16:21:49.113Z"},{"side":"blue","kill_num":4,"t_secs":1149.931,"ts":"2026-03-22T16:23:49.931Z"},{"side":"red","kill_num":11,"t_secs":1509.642,"ts":"2026-03-22T16:29:49.642Z"},{"side":"red","kill_num":12,"t_secs":1509.642,"ts":"2026-03-22T16:29:49.642Z"},{"side":"blue","kill_num":5,"t_secs":1559.113,"ts":"2026-03-22T16:30:39.113Z"},{"side":"blue","kill_num":6,"t_secs":1559.113,"ts":"2026-03-22T16:30:39.113Z"},{"side":"blue","kill_num":7,"t_secs":1569.101,"ts":"2026-03-22T16:30:49.101Z"},{"side":"blue","kill_num":8,"t_secs":1589.115,"ts":"2026-03-22T16:31:09.115Z"}]}