{"game_id":"115654384752393053","match_id":"115654384752393051","league":"LPL","start_time":"2026-02-04T09:00:00Z","blue_team":"WE","red_team":"EDG","summary":{"blue_total_kills":23,"red_total_kills":13,"blue_time_to_5":12.99975,"red_time_to_5":10.165033333333334,"blue_kills_at_10min":3,"red_kills_at_10min":4,"blue_kills_at_15min":5,"red_kills_at_15min":5,"first_to_five":"red"},"kills":[{"side":"red","kill_num":1,"t_secs":239.9,"ts":"2026-02-04T10:14:09.900Z"},{"side":"blue","kill_num":1,"t_secs":359.893,"ts":"2026-02-04T10:16:09.893Z"},{"side":"blue","kill_num":2,"t_secs":559.882,"ts":"2026-02-04T10:19:29.882Z"},{"side":"red","kill_num":2,"t_secs":569.898,"ts":"2026-02-04T10:19:39.898Z"},{"side":"red","kill_num":3,"t_secs":569.898,"ts":"2026-02-04T10:19:39.898Z"},{"side":"blue","kill_num":3,"t_secs":579.951,"ts":"2026-02-04T10:19:49.951Z"},{"side":"red","kill_num":4,"t_secs":579.951,"ts":"2026-02-04T10:19:49.951Z"},{"side":"red","kill_num":5,"t_secs":609.902,"ts":"2026-02-04T10:20:19.902Z"},{"side":"blue","kill_num":4,"t_secs":749.898,"ts":"2026-02-04T10:22:39.898Z"},{"side":"blue","kill_num":5,"t_secs":779.985,"ts":"2026-02-04T10:23:09.985Z"},{"side":"blue","kill_num":6,"t_secs":1319.973,"ts":"2026-02-04T10:32:09.973Z"},{"side":"blue","kill_num":7,"t_secs":1319.973,"ts":"2026-02-04T10:32:09.973Z"},{"side":"blue","kill_num":8,"t_secs":1319.973,"ts":"2026-02-04T10:32:09.973Z"},{"side":"blue","kill_num":9,"t_secs":1409.963,"ts":"2026-02-04T10:33:39.963Z"},{"side":"red","kill_num":6,"t_secs":1409.963,"ts":"2026-02-04T10:33:39.963Z"},{"side":"red","kill_num":7,"t_secs":1419.889,"ts":"2026-02-04T10:33:49.889Z"},{"side":"red","kill_num":8,"t_secs":1429.979,"ts":"2026-02-04T10:33:59.979Z"},{"side":"red","kill_num":9,"t_secs":1469.886,"ts":"2026-02-04T10:34:39.886Z"},{"side":"blue","kill_num":10,"t_secs":1489.957,"ts":"2026-02-04T10:34:59.957Z"},{"side":"red","kill_num":10,"t_secs":1569.939,"ts":"2026-02-04T10:36:19.939Z"},{"side":"blue","kill_num":11,"t_secs":1579.915,"ts":"2026-02-04T10:36:29.915Z"},{"side":"blue","kill_num":12,"t_secs":1579.915,"ts":"2026-02-04T10:36:29.915Z"},{"side":"red","kill_num":11,"t_secs":1579.915,"ts":"2026-02-04T10:36:29.915Z"},{"side":"blue","kill_num":13,"t_secs":1589.867,"ts":"2026-02-04T10:36:39.867Z"},{"side":"blue","kill_num":14,"t_secs":1589.867,"ts":"2026-02-04T10:36:39.867Z"},{"side":"blue","kill_num":15,"t_secs":1739.866,"ts":"2026-02-04T10:39:09.866Z"},{"side":"blue","kill_num":16,"t_secs":1799.869,"ts":"2026-02-04T10:40:09.869Z"},{"side":"blue","kill_num":17,"t_secs":1799.869,"ts":"2026-02-04T10:40:09.869Z"},{"side":"blue","kill_num":18,"t_secs":1809.996,"ts":"2026-02-04T10:40:19.996Z"},{"side":"blue","kill_num":19,"t_secs":2079.872,"ts":"2026-02-04T10:44:49.872Z"},{"side":"blue","kill_num":20,"t_secs":2089.955,"ts":"2026-02-04T10:44:59.955Z"},{"side":"blue","kill_num":21,"t_secs":2089.955,"ts":"2026-02-04T10:44:59.955Z"},{"side":"red","kill_num":12,"t_secs":2089.955,"ts":"2026-02-04T10:44:59.955Z"},{"side":"red","kill_num":13,"t_secs":2089.955,"ts":"2026-02-04T10:44:59.955Z"},{"side":"blue","kill_num":22,"t_secs":2099.863,"ts":"2026-02-04T10:45:09.863Z"},{"side":"blue","kill_num":23,"t_secs":2099.863,"ts":"2026-02-04T10:45:09.863Z"}]}