{"game_id":"116289379852128357","match_id":"116289379852128356","league":"La Ligue Fran\u00e7aise","start_time":"2026-04-23T20:00:00Z","blue_team":"VITB","red_team":"SLY","summary":{"blue_total_kills":6,"red_total_kills":21,"blue_time_to_5":17.664983333333332,"red_time_to_5":10.663216666666667,"blue_kills_at_10min":2,"red_kills_at_10min":4,"blue_kills_at_15min":3,"red_kills_at_15min":8,"first_to_five":"red"},"kills":[{"side":"red","kill_num":1,"t_secs":179.886,"ts":"2026-04-23T19:38:49.886Z"},{"side":"red","kill_num":2,"t_secs":249.675,"ts":"2026-04-23T19:39:59.675Z"},{"side":"red","kill_num":3,"t_secs":409.487,"ts":"2026-04-23T19:42:39.487Z"},{"side":"blue","kill_num":1,"t_secs":499.714,"ts":"2026-04-23T19:44:09.714Z"},{"side":"red","kill_num":4,"t_secs":499.714,"ts":"2026-04-23T19:44:09.714Z"},{"side":"blue","kill_num":2,"t_secs":539.58,"ts":"2026-04-23T19:44:49.580Z"},{"side":"red","kill_num":5,"t_secs":639.793,"ts":"2026-04-23T19:46:29.793Z"},{"side":"red","kill_num":6,"t_secs":639.793,"ts":"2026-04-23T19:46:29.793Z"},{"side":"red","kill_num":7,"t_secs":689.869,"ts":"2026-04-23T19:47:19.869Z"},{"side":"blue","kill_num":3,"t_secs":739.851,"ts":"2026-04-23T19:48:09.851Z"},{"side":"red","kill_num":8,"t_secs":829.903,"ts":"2026-04-23T19:49:39.903Z"},{"side":"red","kill_num":9,"t_secs":1029.991,"ts":"2026-04-23T19:52:59.991Z"},{"side":"red","kill_num":10,"t_secs":1029.991,"ts":"2026-04-23T19:52:59.991Z"},{"side":"blue","kill_num":4,"t_secs":1049.43,"ts":"2026-04-23T19:53:19.430Z"},{"side":"blue","kill_num":5,"t_secs":1059.899,"ts":"2026-04-23T19:53:29.899Z"},{"side":"red","kill_num":11,"t_secs":1129.546,"ts":"2026-04-23T19:54:39.546Z"},{"side":"red","kill_num":12,"t_secs":1129.546,"ts":"2026-04-23T19:54:39.546Z"},{"side":"blue","kill_num":6,"t_secs":1299.613,"ts":"2026-04-23T19:57:29.613Z"},{"side":"red","kill_num":13,"t_secs":1449.871,"ts":"2026-04-23T19:59:59.871Z"},{"side":"red","kill_num":14,"t_secs":1459.763,"ts":"2026-04-23T20:00:09.763Z"},{"side":"red","kill_num":15,"t_secs":1719.801,"ts":"2026-04-23T20:04:29.801Z"},{"side":"red","kill_num":16,"t_secs":1739.48,"ts":"2026-04-23T20:04:49.480Z"},{"side":"red","kill_num":17,"t_secs":1909.746,"ts":"2026-04-23T20:07:39.746Z"},{"side":"red","kill_num":18,"t_secs":1929.831,"ts":"2026-04-23T20:07:59.831Z"},{"side":"red","kill_num":19,"t_secs":1929.831,"ts":"2026-04-23T20:07:59.831Z"},{"side":"red","kill_num":20,"t_secs":1949.862,"ts":"2026-04-23T20:08:19.862Z"},{"side":"red","kill_num":21,"t_secs":1949.862,"ts":"2026-04-23T20:08:19.862Z"}]}